README.md
pyproject.toml
src/health_calc_pack_python.egg-info/PKG-INFO
src/health_calc_pack_python.egg-info/SOURCES.txt
src/health_calc_pack_python.egg-info/dependency_links.txt
src/health_calc_pack_python.egg-info/top_level.txt
src/person/Person.py
src/person/__init__.py
src/test/test_Person.py